{"advanced_system-ctl.md":"e08d9ad5","apps_android.md":"e807e8ed","apps_collaboration.md":"05947e86","apps_communication.md":"dc582712","apps_media.md":"77c159a8","exclusive_code.md":"6556f157","exclusive_image.md":"8f0704ce","exclusive_media.md":"3a3ada7e","exclusive_vedio.md":"e08c4366","index.md":"d089fad8","postscript_about.md":"256fa93c","postscript_contribute.md":"f50f1b2f","postscript_contributor-covenant.md":"45a81ef2","postscript_copyright.md":"9c412105","rookie_basic-install-detail.md":"7941b644","advanced_power-ctl.md":"000b1889","apps_remote.md":"cb23ba75","postscript_postscript.md":"f14f0e10","exclusive_audio.md":"88acffb8","advanced_optional-cfg-1.md":"3d9baf5f","advanced_debug.md":"b1fa6507","advanced_make-install-disk.md":"68450e57","advanced_btrfs.md":"b4bee558","rookie_basic-install.md":"fa837ba1","advanced_beauty-3.md":"f98cde52","advanced_optional-cfg-2.md":"b3a9edfd","rookie_desktop-env-and-app.md":"78ef8442","prologue.md":"9edd1ad1","apps_play.md":"851b8104","apps_daily.md":"d0f38566","prepare_head-on-blow.md":"17b0c37c","advanced_beauty-1.md":"e9e8c4d3","prepare_understand.md":"cf6509e1","apps_office.md":"622f7298","rookie_pre-virt.md":"82e06867","rookie_transparent.md":"1d58f7e9","rookie_pre-install.md":"c556922d","advanced_beauty-2.md":"afa68975","rookie_graphic-driver.md":"7f257165"}
